{
    "last_check_time": "2026-04-04T13:45:43",
    "seen_ids": [
        "145657",
        "145760",
        "145865",
        "145550",
        "145789",
        "145913",
        "145548",
        "145638",
        "145629",
        "145903",
        "145554",
        "145677",
        "145812",
        "145923",
        "145840",
        "145853",
        "145738",
        "145669",
        "145828",
        "145867",
        "145569",
        "145558",
        "145706"
    ],
    "metadata": {
        "window_size": 50,
        "total_checked": 924
    }
}