{
    "last_check_time": "2026-03-28T05:18:48",
    "seen_ids": [
        "145554",
        "145840",
        "145706",
        "145812",
        "145853",
        "145789",
        "145558",
        "145828",
        "145865",
        "145903",
        "145550",
        "145867",
        "145629",
        "145738",
        "145669",
        "145677",
        "145638",
        "145657",
        "145760",
        "145548",
        "145569"
    ],
    "metadata": {
        "window_size": 50,
        "total_checked": 748
    }
}