{
    "last_check_time": "2026-05-16T18:50:43",
    "seen_ids": [
        "145706",
        "146090",
        "145812",
        "145789",
        "145865",
        "145946",
        "145828",
        "145971",
        "145558",
        "146008",
        "145677",
        "145853",
        "145629",
        "145738",
        "145961",
        "146042",
        "145638",
        "146069",
        "145903",
        "145657",
        "145548",
        "145867",
        "146068",
        "146015",
        "145981",
        "146017",
        "145760",
        "145669",
        "145550",
        "146059",
        "145923",
        "145997",
        "146029",
        "145913",
        "145953",
        "145840",
        "145554",
        "146014",
        "145569",
        "145957"
    ],
    "metadata": {
        "window_size": 50,
        "total_checked": 1632
    }
}