{
    "last_check_time": "2026-07-18T19:58:41",
    "seen_ids": [
        "145997",
        "145923",
        "146014",
        "146017",
        "145853",
        "146275",
        "146263",
        "145657",
        "146194",
        "145865",
        "146267",
        "145706",
        "146202",
        "145638",
        "146069",
        "146008",
        "146029",
        "146185",
        "146195",
        "146235",
        "146015",
        "146264",
        "146090",
        "146122",
        "146059",
        "146042",
        "146295",
        "145840",
        "145812",
        "145669",
        "145760",
        "145971",
        "146179",
        "146294",
        "145981",
        "145903",
        "145913",
        "145953",
        "145957",
        "145946",
        "146158",
        "145738",
        "145789",
        "145677",
        "145867",
        "146305",
        "146068",
        "146173",
        "145828",
        "145961"
    ],
    "metadata": {
        "window_size": 50,
        "total_checked": 2266
    }
}